{
    "minify": true,
    "sourcemap": false,
    "bundleOnlyRequiredNodes": true,
    "outputDir": "build",
    "configNodesFilePath": "/home/rof13thfloor/.node-red/.config.nodes.json",
    "caPath": "/home/rof13thfloor/work/ssl/ca.pem",
    "certPath": "/home/rof13thfloor/work/ssl/server.cert",
    "keyPath": "/home/rof13thfloor/work/ssl/server.key",
    "flowFilePath": "./flows/Flow-Evaluation/Download-based/Object-Detection.json",
    "manifestFilePath": "./manifests/files.toml",
    "remoteDir": "/home/kth-rof13thfloor/gramine-test",
    "uploadBundle": true,
    "startEnclave": false,
    "encryptUserDir": false
}